{
  "id": 48298742,
  "url": "https://www.linkedin.com/company/linkit-holding-b.v.",
  "hash": "b297c669100ef4559e04ddb77eb2842f",
  "name": "LINKIT holding B.V.",
  "website": null,
  "size": "1 employee",
  "industry": "Financial Services",
  "description": null,
  "followers": null,
  "founded": null,
  "headquarters_city": null,
  "headquarters_country": null,
  "headquarters_state": null,
  "headquarters_street1": null,
  "headquarters_street2": null,
  "headquarters_zip": null,
  "logo_url": "https://static.licdn.com/aero-v1/sc/h/cs8pjfgyw96g44ln9r7tct85f",
  "created": "2021-09-24 21:59:06",
  "last_updated": "2025-07-08 01:24:08",
  "last_response_code": 200,
  "type": null,
  "headquarters_new_address": "DE MEERN",
  "employees_count": null,
  "headquarters_country_restored": null,
  "headquarters_country_parsed": "Russia",
  "company_shorthand_name": "linkit-holding-b.v.",
  "company_shorthand_name_hash": "a41d6e06742537adada0240e20c628e6",
  "canonical_url": "https://nl.linkedin.com/company/linkit-holding-b.v.",
  "canonical_hash": "d03b75721c458b82041b67ff52a7b4f6",
  "canonical_shorthand_name": "linkit-holding-b.v.",
  "canonical_shorthand_name_hash": "a41d6e06742537adada0240e20c628e6",
  "deleted": 0,
  "last_updated_ux": 1751937847,
  "source_id": 25090744,
  "company_affiliated_collection": [],
  "company_also_viewed_collection": [],
  "company_crunchbase_info_collection": [],
  "company_featured_employees_collection": [],
  "company_featured_investors_collection": [],
  "company_funding_rounds_collection": [],
  "company_locations_collection": [
    {
      "id": 47970874,
      "company_id": 48298742,
      "location_address": "Rijnzathe 9; DE MEERN, NL",
      "is_primary": 0,
      "created": "2021-09-24 21:59:05",
      "last_updated": "2023-09-02 21:28:29",
      "deleted": 1
    },
    {
      "id": 127090802,
      "company_id": 48298742,
      "location_address": "Rijnzathe 9; DE MEERN, 3454PV, NL",
      "is_primary": 0,
      "created": "2023-09-02 21:28:29",
      "last_updated": "2025-07-08 01:24:07",
      "deleted": 0
    }
  ],
  "company_similar_collection": [],
  "company_specialties_collection": [],
  "company_stock_info_collection": [],
  "company_updates_collection": []
}